CHANGELOG.rst
MANIFEST.in
README.rst
setup.py
src/ua2/__init__.py
src/ua2.forms.egg-info/PKG-INFO
src/ua2.forms.egg-info/SOURCES.txt
src/ua2.forms.egg-info/dependency_links.txt
src/ua2.forms.egg-info/eager_resources.txt
src/ua2.forms.egg-info/namespace_packages.txt
src/ua2.forms.egg-info/not-zip-safe
src/ua2.forms.egg-info/requires.txt
src/ua2.forms.egg-info/top_level.txt
src/ua2/forms/__init__.py
src/ua2/forms/base.py
src/ua2/forms/fields.py
src/ua2/forms/forms.py
src/ua2/forms/widgets.py
src/ua2/forms/templates/__init__.py
src/ua2/forms/templatetags/__init__.py
src/ua2/forms/templatetags/ua2form.py