Metadata-Version: 1.1
Name: ua2.forms
Version: 0.5.3
Summary: Alternative package for rendering tables
Home-page: https://bitbucket.org/ua2web/ua2.forms
Author: Viacheslav Vic Bukhantsov
Author-email: vic@sdh.com.ua
License: BSD License
Platform: OS Independent
Classifier: Development Status :: 5 - Production/Stable
Classifier: Intended Audience :: Developers
Classifier: Framework :: Django
Classifier: License :: OSI Approved :: BSD License
Classifier: Operating System :: OS Independent
Classifier: Programming Language :: Python
Classifier: Programming Language :: Python :: 2
Classifier: Programming Language :: Python :: 3
Classifier: Topic :: Internet :: WWW/HTTP :: Dynamic Content
Classifier: Topic :: Software Development
Classifier: Topic :: Software Development :: Libraries
